paq_proyecto/__init__.py
paq_proyecto/estadisticos.py
paq_proyecto-0.0.1.dist-info/LICENSE
paq_proyecto-0.0.1.dist-info/METADATA
paq_proyecto-0.0.1.dist-info/WHEEL
paq_proyecto-0.0.1.dist-info/top_level.txt
paq_proyecto-0.0.1.dist-info/RECORD
