Metadata-Version: 2.1
Name: paq-proyecto
Version: 0.0.1
Summary: Paquete que permite realizar calculos estaditicos
Author-email: Damian Leon <damianleon@usantotomas.edu.co>
License: MIT License        
Project-URL: Homepage, https://github.com/IanDam/paq_proyecto
Project-URL: Bug Tracker, https://github.com/IanDam/paq_proyecto/issues
Classifier: Programming Language :: Python :: 3
Classifier: License :: OSI Approved :: MIT License
Classifier: Operating System :: OS Independent
Requires-Python: >=3.7
License-File: LICENSE
